MANIFEST.in
README
setup.py
pylatus_brokers/__init__.py
pylatus_brokers/chunks.py
pylatus_brokers/constants.py
pylatus_brokers/dcu_broker.py
pylatus_brokers/ppu_broker.py
pylatus_brokers/tools.py
pylatus_brokers.egg-info/PKG-INFO
pylatus_brokers.egg-info/SOURCES.txt
pylatus_brokers.egg-info/dependency_links.txt
pylatus_brokers.egg-info/entry_points.txt
pylatus_brokers.egg-info/requires.txt
pylatus_brokers.egg-info/top_level.txt