Metadata-Version: 1.0
Name: pylatus-brokers
Version: 2017.11.26
Summary: Data brokers for Pylatus
Home-page: https://hg.3lp.cx/pylatus-brokers
Author: Vadim Dyadkin
Author-email: diadkin@esrf.fr
License: GPLv3
Platform: UNKNOWN
